deprecated/data_processing.py
deprecated/fast_kde copy.py
deprecated/fast_kde_cl_new.py
deprecated/fast_kde_ds.py
deprecated/gen_params.py
deprecated/generate_data_updated_myownversion.py
deprecated/hard_kmeans_algo.py
deprecated/soft_kmeans_algo.py
sa_ebm/__init__.py
sa_ebm/run.py
sa_ebm/algorithms/__init__.py
sa_ebm/algorithms/algorithm.py
sa_ebm/data/__init__.py
sa_ebm/data/params.json
sa_ebm/data/samples/10|100_0.csv
sa_ebm/data/samples/5|50_0.csv
sa_ebm/test/gen.py
sa_ebm/test/test.py
sa_ebm/utils/__init__.py
sa_ebm/utils/data_processing.py
sa_ebm/utils/fast_kde.py
sa_ebm/utils/generate_data.py
sa_ebm/utils/kmeans.py
sa_ebm/utils/logging_utils.py
sa_ebm/utils/runners.py
sa_ebm/utils/save_kde_dict.py
sa_ebm/utils/visualization.py
sa_ebm-1.12.dist-info/LICENSE
sa_ebm-1.12.dist-info/METADATA
sa_ebm-1.12.dist-info/WHEEL
sa_ebm-1.12.dist-info/top_level.txt
sa_ebm-1.12.dist-info/RECORD
