Metadata-Version: 2.1
Name: sa_ebm
Version: 1.12
Summary: Stage-Aware Event-Based Modeling for Disease Progression
Author-email: Hongtao Hao and Joseph Austerweil <hongtaoh@cs.wisc.edu>
Project-URL: Homepage, https://github.com/hongtaoh/sa_ebm
Classifier: Programming Language :: Python :: 3
Classifier: License :: OSI Approved :: MIT License
Classifier: Operating System :: OS Independent
Requires-Python: >=3.7
License-File: LICENSE
Requires-Dist: pandas
Requires-Dist: numpy
Requires-Dist: scipy
Requires-Dist: matplotlib
Requires-Dist: seaborn
Requires-Dist: scikit-learn
Requires-Dist: numba
